orafmt/__init__.py
orafmt/cli.py
orafmt/formatter/format.js
orafmt/formatter/trivadis_advanced_format.xml
orafmt/formatter/trivadis_custom_format.arbori
orafmt-1.0.2.dist-info/entry_points.txt
orafmt-1.0.2.dist-info/LICENSE
orafmt-1.0.2.dist-info/METADATA
orafmt-1.0.2.dist-info/WHEEL
orafmt-1.0.2.dist-info/RECORD
