Metadata-Version: 2.1
Name: orafmt
Version: 1.0.2
Summary: A Python tool for formatting Oracle SQL files with SQLcl and custom formatting options.
Home-page: https://github.com/YourUsername/orafmt
License: MIT
Keywords: oracle,sql,formatter,pre-commit,sqlcl
Author: Semjon Geist
Author-email: mail@semjon-geist.de
Requires-Python: >=3.8,<4.0
Classifier: License :: OSI Approved :: MIT License
Classifier: Operating System :: OS Independent
Classifier: Programming Language :: Python :: 3
Classifier: Programming Language :: Python :: 3.8
Classifier: Programming Language :: Python :: 3.9
Classifier: Programming Language :: Python :: 3.10
Classifier: Programming Language :: Python :: 3.11
Classifier: Programming Language :: Python :: 3.12
Classifier: Programming Language :: Python :: 3.13
Project-URL: Repository, https://github.com/YourUsername/orafmt
